{
  "generated_at": "2026-05-20T16:22:51Z",
  "exchange": "kraken",
  "cache_hit": false,
  "portfolio": {
    "total_usd": 28.8,
    "stablecoins_usd": 11.43,
    "balances": [
      {
        "asset": "USDT",
        "symbol": "USDT",
        "coingecko_id": "tether",
        "qty": 11.44376913,
        "price_usd": 0.999085,
        "usd_value": 11.43,
        "change_24h_pct": -0.01,
        "avg_buy": null,
        "pnl_pct": null,
        "is_stablecoin": true
      },
      {
        "asset": "XXBT",
        "symbol": "BTC",
        "coingecko_id": "bitcoin",
        "qty": 8.581e-05,
        "price_usd": 77208,
        "usd_value": 6.63,
        "change_24h_pct": 0.96,
        "avg_buy": 90111.0,
        "pnl_pct": -14.3,
        "is_stablecoin": false
      },
      {
        "asset": "SOL",
        "symbol": "SOL",
        "coingecko_id": "solana",
        "qty": 0.0581749358,
        "price_usd": 85.81,
        "usd_value": 4.99,
        "change_24h_pct": 1.83,
        "avg_buy": 151.0,
        "pnl_pct": -43.2,
        "is_stablecoin": false
      },
      {
        "asset": "PENGU",
        "symbol": "PENGU",
        "coingecko_id": "pudgy-penguins",
        "qty": 360.2316,
        "price_usd": 0.00930256,
        "usd_value": 3.35,
        "change_24h_pct": 9.62,
        "avg_buy": null,
        "pnl_pct": null,
        "is_stablecoin": false
      },
      {
        "asset": "OPN",
        "symbol": "OPN",
        "coingecko_id": "opinion",
        "qty": 8.428,
        "price_usd": 0.177382,
        "usd_value": 1.49,
        "change_24h_pct": 5.37,
        "avg_buy": 0.3326,
        "pnl_pct": -46.7,
        "is_stablecoin": false
      },
      {
        "asset": "XETH",
        "symbol": "ETH",
        "coingecko_id": "ethereum",
        "qty": 0.0004240981,
        "price_usd": 2130.55,
        "usd_value": 0.9,
        "change_24h_pct": 1.03,
        "avg_buy": 3151.0,
        "pnl_pct": -32.4,
        "is_stablecoin": false
      },
      {
        "asset": "BABY",
        "symbol": "BABY",
        "coingecko_id": "babylon",
        "qty": 0.01664,
        "price_usd": 0.01534954,
        "usd_value": 0.0,
        "change_24h_pct": -1.1,
        "avg_buy": 0.028,
        "pnl_pct": -45.2,
        "is_stablecoin": false
      },
      {
        "asset": "BONK",
        "symbol": "BONK",
        "coingecko_id": null,
        "qty": 1.97,
        "price_usd": null,
        "usd_value": 0.0,
        "change_24h_pct": null,
        "avg_buy": null,
        "pnl_pct": null,
        "is_stablecoin": false
      },
      {
        "asset": "EIGEN",
        "symbol": "EIGEN",
        "coingecko_id": "eigenlayer",
        "qty": 0.005103,
        "price_usd": 0.194633,
        "usd_value": 0.0,
        "change_24h_pct": 4.39,
        "avg_buy": 0.3,
        "pnl_pct": -35.1,
        "is_stablecoin": false
      },
      {
        "asset": "ETH.B",
        "symbol": "ETH.B",
        "coingecko_id": null,
        "qty": 0.0018733166,
        "price_usd": null,
        "usd_value": 0.0,
        "change_24h_pct": null,
        "avg_buy": null,
        "pnl_pct": null,
        "is_stablecoin": false
      },
      {
        "asset": "FARTCOIN",
        "symbol": "FARTCOIN",
        "coingecko_id": null,
        "qty": 5e-05,
        "price_usd": null,
        "usd_value": 0.0,
        "change_24h_pct": null,
        "avg_buy": null,
        "pnl_pct": null,
        "is_stablecoin": false
      },
      {
        "asset": "PEPE",
        "symbol": "PEPE",
        "coingecko_id": null,
        "qty": 3.27,
        "price_usd": null,
        "usd_value": 0.0,
        "change_24h_pct": null,
        "avg_buy": null,
        "pnl_pct": null,
        "is_stablecoin": false
      },
      {
        "asset": "SHIB",
        "symbol": "SHIB",
        "coingecko_id": null,
        "qty": 2.20495,
        "price_usd": null,
        "usd_value": 0.0,
        "change_24h_pct": null,
        "avg_buy": null,
        "pnl_pct": null,
        "is_stablecoin": false
      },
      {
        "asset": "USDG",
        "symbol": "USDG",
        "coingecko_id": null,
        "qty": 0.00045011,
        "price_usd": null,
        "usd_value": 0.0,
        "change_24h_pct": null,
        "avg_buy": null,
        "pnl_pct": null,
        "is_stablecoin": false
      },
      {
        "asset": "USDG.B",
        "symbol": "USDG.B",
        "coingecko_id": null,
        "qty": 1.09176365,
        "price_usd": null,
        "usd_value": 0.0,
        "change_24h_pct": null,
        "avg_buy": null,
        "pnl_pct": null,
        "is_stablecoin": false
      },
      {
        "asset": "XBT.B",
        "symbol": "XBT.B",
        "coingecko_id": null,
        "qty": 6.38712e-05,
        "price_usd": null,
        "usd_value": 0.0,
        "change_24h_pct": null,
        "avg_buy": null,
        "pnl_pct": null,
        "is_stablecoin": false
      },
      {
        "asset": "XBT.M",
        "symbol": "XBT.M",
        "coingecko_id": null,
        "qty": 1.04645e-05,
        "price_usd": null,
        "usd_value": 0.0,
        "change_24h_pct": null,
        "avg_buy": null,
        "pnl_pct": null,
        "is_stablecoin": false
      },
      {
        "asset": "XXDG",
        "symbol": "XXDG",
        "coingecko_id": null,
        "qty": 0.00013067,
        "price_usd": null,
        "usd_value": 0.0,
        "change_24h_pct": null,
        "avg_buy": null,
        "pnl_pct": null,
        "is_stablecoin": false
      },
      {
        "asset": "XXRP",
        "symbol": "XXRP",
        "coingecko_id": null,
        "qty": 3.51733881,
        "price_usd": null,
        "usd_value": 0.0,
        "change_24h_pct": null,
        "avg_buy": null,
        "pnl_pct": null,
        "is_stablecoin": false
      },
      {
        "asset": "ZEUR",
        "symbol": "ZEUR",
        "coingecko_id": null,
        "qty": 0.2991,
        "price_usd": null,
        "usd_value": 0.0,
        "change_24h_pct": null,
        "avg_buy": null,
        "pnl_pct": null,
        "is_stablecoin": false
      },
      {
        "asset": "ZUSD",
        "symbol": "ZUSD",
        "coingecko_id": "usd-coin",
        "qty": 0.0014,
        "price_usd": 0.999716,
        "usd_value": 0.0,
        "change_24h_pct": -0.0,
        "avg_buy": null,
        "pnl_pct": null,
        "is_stablecoin": true
      }
    ],
    "open_orders": [],
    "recent_trades": [
      {
        "order_id": "OV4QV3-FH7BV-XNHHYD",
        "pair": "PENGUUSD",
        "type": "sell",
        "order_type": "limit",
        "price_executed": 0.00704,
        "volume": 710.32817,
        "volume_filled": 710.32817,
        "cost_usd": 5.00142,
        "fee_usd": 0.02001,
        "status": "closed",
        "closed_at": "2026-04-15T14:00:44Z"
      }
    ],
    "prices": {
      "BABYUSD": {
        "bid": 0.01529,
        "ask": 0.01535,
        "last": 0.01536,
        "high_24h": 0.01578,
        "low_24h": 0.0151,
        "volume_24h": 2305473.34408,
        "vwap_24h": 0.015353341,
        "trades_24h": 941
      },
      "EIGENUSD": {
        "bid": 0.1942,
        "ask": 0.1946,
        "last": 0.1944,
        "high_24h": 0.1985,
        "low_24h": 0.1822,
        "volume_24h": 321238.21132,
        "vwap_24h": 0.1883494,
        "trades_24h": 423
      },
      "XETHZUSD": {
        "bid": 2131.08,
        "ask": 2131.09,
        "last": 2131.1,
        "high_24h": 2147.16,
        "low_24h": 2101.0,
        "volume_24h": 17490.19786916,
        "vwap_24h": 2121.82922,
        "trades_24h": 16152
      },
      "OPNUSD": {
        "bid": 0.177,
        "ask": 0.1781,
        "last": 0.1769,
        "high_24h": 0.1787,
        "low_24h": 0.167,
        "volume_24h": 161372.9033,
        "vwap_24h": 0.17202819,
        "trades_24h": 195
      },
      "PENGUUSD": {
        "bid": 0.009287,
        "ask": 0.009296,
        "last": 0.009295,
        "high_24h": 0.009415,
        "low_24h": 0.008495,
        "volume_24h": 166089060.01579,
        "vwap_24h": 0.008828635,
        "trades_24h": 4545
      },
      "SOLUSD": {
        "bid": 85.84,
        "ask": 85.85,
        "last": 85.86,
        "high_24h": 86.37,
        "low_24h": 83.76,
        "volume_24h": 273177.61331607,
        "vwap_24h": 84.89834,
        "trades_24h": 15915
      },
      "XXBTZUSD": {
        "bid": 77197.0,
        "ask": 77197.1,
        "last": 77197.1,
        "high_24h": 77750.0,
        "low_24h": 76459.6,
        "volume_24h": 1143.04417517,
        "vwap_24h": 77061.93829,
        "trades_24h": 45847
      }
    }
  }
}