{
  "generated_at": "2026-03-20T19:52:57Z",
  "exchange": "kraken",
  "cache_hit": false,
  "portfolio": {
    "total_usd": 15.87,
    "stablecoins_usd": 0.01,
    "balances": [
      {
        "asset": "PENGU",
        "symbol": "PENGU",
        "coingecko_id": "pudgy-penguins",
        "qty": 1873.2,
        "price_usd": 0.00705289,
        "usd_value": 13.21,
        "change_24h_pct": -0.36,
        "avg_buy": null,
        "pnl_pct": null,
        "is_stablecoin": false
      },
      {
        "asset": "XXBT",
        "symbol": "BT",
        "coingecko_id": "bitcoin",
        "qty": 2.364e-05,
        "price_usd": 69960,
        "usd_value": 1.65,
        "change_24h_pct": -0.46,
        "avg_buy": 90111.0,
        "pnl_pct": -22.4,
        "is_stablecoin": false
      },
      {
        "asset": "OPN",
        "symbol": "OPN",
        "coingecko_id": "opinion",
        "qty": 3.498,
        "price_usd": 0.28084,
        "usd_value": 0.98,
        "change_24h_pct": -7.58,
        "avg_buy": 0.3326,
        "pnl_pct": -15.6,
        "is_stablecoin": false
      },
      {
        "asset": "USDT",
        "symbol": "USDT",
        "coingecko_id": "tether",
        "qty": 0.01001724,
        "price_usd": 0.999846,
        "usd_value": 0.01,
        "change_24h_pct": -0.03,
        "avg_buy": null,
        "pnl_pct": null,
        "is_stablecoin": true
      },
      {
        "asset": "XETH",
        "symbol": "ETH",
        "coingecko_id": "ethereum",
        "qty": 4.0016e-06,
        "price_usd": 2126.73,
        "usd_value": 0.01,
        "change_24h_pct": -0.71,
        "avg_buy": 3151.0,
        "pnl_pct": -32.5,
        "is_stablecoin": false
      },
      {
        "asset": "BABY",
        "symbol": "BABY",
        "coingecko_id": "babylon",
        "qty": 0.00348,
        "price_usd": 0.01303761,
        "usd_value": 0.0,
        "change_24h_pct": 2.43,
        "avg_buy": 0.028,
        "pnl_pct": -53.4,
        "is_stablecoin": false
      },
      {
        "asset": "EIGEN",
        "symbol": "EIGEN",
        "coingecko_id": "eigenlayer",
        "qty": 0.003366,
        "price_usd": 0.191352,
        "usd_value": 0.0,
        "change_24h_pct": -1.03,
        "avg_buy": 0.3,
        "pnl_pct": -36.2,
        "is_stablecoin": false
      },
      {
        "asset": "ETH.B",
        "symbol": "ETH.B",
        "coingecko_id": null,
        "qty": 0.0018672113,
        "price_usd": null,
        "usd_value": 0.0,
        "change_24h_pct": null,
        "avg_buy": null,
        "pnl_pct": null,
        "is_stablecoin": false
      },
      {
        "asset": "SOL",
        "symbol": "SOL",
        "coingecko_id": "solana",
        "qty": 6.2624e-06,
        "price_usd": 88.66,
        "usd_value": 0.0,
        "change_24h_pct": -0.3,
        "avg_buy": 151.0,
        "pnl_pct": -41.3,
        "is_stablecoin": false
      },
      {
        "asset": "USDG",
        "symbol": "USDG",
        "coingecko_id": null,
        "qty": 1.08310033,
        "price_usd": null,
        "usd_value": 0.0,
        "change_24h_pct": null,
        "avg_buy": null,
        "pnl_pct": null,
        "is_stablecoin": false
      },
      {
        "asset": "XBT.B",
        "symbol": "XBT.B",
        "coingecko_id": null,
        "qty": 6.38547e-05,
        "price_usd": null,
        "usd_value": 0.0,
        "change_24h_pct": null,
        "avg_buy": null,
        "pnl_pct": null,
        "is_stablecoin": false
      },
      {
        "asset": "XBT.M",
        "symbol": "XBT.M",
        "coingecko_id": null,
        "qty": 1.04627e-05,
        "price_usd": null,
        "usd_value": 0.0,
        "change_24h_pct": null,
        "avg_buy": null,
        "pnl_pct": null,
        "is_stablecoin": false
      },
      {
        "asset": "ZEUR",
        "symbol": "ZEUR",
        "coingecko_id": null,
        "qty": 0.0092,
        "price_usd": null,
        "usd_value": 0.0,
        "change_24h_pct": null,
        "avg_buy": null,
        "pnl_pct": null,
        "is_stablecoin": false
      }
    ],
    "open_orders": [],
    "recent_trades": [],
    "prices": {
      "BABYUSD": {
        "bid": 0.01301,
        "ask": 0.01304,
        "last": 0.01297,
        "high_24h": 0.01338,
        "low_24h": 0.01265,
        "volume_24h": 2743159.4408,
        "vwap_24h": 0.01295235,
        "trades_24h": 429
      },
      "EIGENUSD": {
        "bid": 0.1915,
        "ask": 0.1916,
        "last": 0.1909,
        "high_24h": 0.2027,
        "low_24h": 0.1905,
        "volume_24h": 199284.03928,
        "vwap_24h": 0.1974917,
        "trades_24h": 360
      },
      "XETHZUSD": {
        "bid": 2128.56,
        "ask": 2128.57,
        "last": 2128.3,
        "high_24h": 2176.58,
        "low_24h": 2117.15,
        "volume_24h": 45796.94834158,
        "vwap_24h": 2141.91847,
        "trades_24h": 28943
      },
      "OPNUSD": {
        "bid": 0.2803,
        "ask": 0.2814,
        "last": 0.2771,
        "high_24h": 0.3042,
        "low_24h": 0.2767,
        "volume_24h": 169818.43403,
        "vwap_24h": 0.29042047,
        "trades_24h": 388
      },
      "PENGUUSD": {
        "bid": 0.007062,
        "ask": 0.007065,
        "last": 0.007063,
        "high_24h": 0.007385,
        "low_24h": 0.006964,
        "volume_24h": 160181488.73702,
        "vwap_24h": 0.007209465,
        "trades_24h": 4312
      },
      "SOLUSD": {
        "bid": 88.88,
        "ask": 88.89,
        "last": 88.87,
        "high_24h": 90.45,
        "low_24h": 88.14,
        "volume_24h": 197246.00405351,
        "vwap_24h": 89.10624,
        "trades_24h": 15552
      },
      "XXBTZUSD": {
        "bid": 70005.0,
        "ask": 70005.1,
        "last": 70005.0,
        "high_24h": 71340.6,
        "low_24h": 69400.0,
        "volume_24h": 2006.04513557,
        "vwap_24h": 70242.68888,
        "trades_24h": 56575
      }
    }
  }
}