{
  "generated_at": "2026-03-18T22:56:47Z",
  "exchange": "kraken",
  "cache_hit": false,
  "portfolio": {
    "total_usd": 16.64,
    "stablecoins_usd": 0.01,
    "balances": [
      {
        "asset": "PENGU",
        "symbol": "PENGU",
        "coingecko_id": "pudgy-penguins",
        "qty": 1873.2,
        "price_usd": 0.00746869,
        "usd_value": 13.99,
        "change_24h_pct": -6.0,
        "avg_buy": null,
        "pnl_pct": null,
        "is_stablecoin": false
      },
      {
        "asset": "XXBT",
        "symbol": "BT",
        "coingecko_id": "bitcoin",
        "qty": 2.364e-05,
        "price_usd": 71103,
        "usd_value": 1.68,
        "change_24h_pct": -4.32,
        "avg_buy": 90111.0,
        "pnl_pct": -21.1,
        "is_stablecoin": false
      },
      {
        "asset": "OPN",
        "symbol": "OPN",
        "coingecko_id": "opinion",
        "qty": 3.498,
        "price_usd": 0.272039,
        "usd_value": 0.95,
        "change_24h_pct": -9.33,
        "avg_buy": 0.3326,
        "pnl_pct": -18.2,
        "is_stablecoin": false
      },
      {
        "asset": "USDT",
        "symbol": "USDT",
        "coingecko_id": "tether",
        "qty": 0.01001724,
        "price_usd": 0.999997,
        "usd_value": 0.01,
        "change_24h_pct": -0.01,
        "avg_buy": null,
        "pnl_pct": null,
        "is_stablecoin": true
      },
      {
        "asset": "XETH",
        "symbol": "ETH",
        "coingecko_id": "ethereum",
        "qty": 4.0016e-06,
        "price_usd": 2192.36,
        "usd_value": 0.01,
        "change_24h_pct": -5.89,
        "avg_buy": 3151.0,
        "pnl_pct": -30.4,
        "is_stablecoin": false
      },
      {
        "asset": "BABY",
        "symbol": "BABY",
        "coingecko_id": "babylon",
        "qty": 0.00348,
        "price_usd": 0.01289295,
        "usd_value": 0.0,
        "change_24h_pct": -6.65,
        "avg_buy": 0.028,
        "pnl_pct": -54.0,
        "is_stablecoin": false
      },
      {
        "asset": "EIGEN",
        "symbol": "EIGEN",
        "coingecko_id": "eigenlayer",
        "qty": 0.003366,
        "price_usd": 0.203293,
        "usd_value": 0.0,
        "change_24h_pct": -7.55,
        "avg_buy": 0.3,
        "pnl_pct": -32.2,
        "is_stablecoin": false
      },
      {
        "asset": "ETH.B",
        "symbol": "ETH.B",
        "coingecko_id": null,
        "qty": 0.0018672113,
        "price_usd": null,
        "usd_value": 0.0,
        "change_24h_pct": null,
        "avg_buy": null,
        "pnl_pct": null,
        "is_stablecoin": false
      },
      {
        "asset": "SOL",
        "symbol": "SOL",
        "coingecko_id": "solana",
        "qty": 6.2624e-06,
        "price_usd": 90.01,
        "usd_value": 0.0,
        "change_24h_pct": -5.5,
        "avg_buy": 151.0,
        "pnl_pct": -40.4,
        "is_stablecoin": false
      },
      {
        "asset": "USDG",
        "symbol": "USDG",
        "coingecko_id": null,
        "qty": 1.08310033,
        "price_usd": null,
        "usd_value": 0.0,
        "change_24h_pct": null,
        "avg_buy": null,
        "pnl_pct": null,
        "is_stablecoin": false
      },
      {
        "asset": "XBT.B",
        "symbol": "XBT.B",
        "coingecko_id": null,
        "qty": 6.38547e-05,
        "price_usd": null,
        "usd_value": 0.0,
        "change_24h_pct": null,
        "avg_buy": null,
        "pnl_pct": null,
        "is_stablecoin": false
      },
      {
        "asset": "XBT.M",
        "symbol": "XBT.M",
        "coingecko_id": null,
        "qty": 1.04627e-05,
        "price_usd": null,
        "usd_value": 0.0,
        "change_24h_pct": null,
        "avg_buy": null,
        "pnl_pct": null,
        "is_stablecoin": false
      },
      {
        "asset": "ZEUR",
        "symbol": "ZEUR",
        "coingecko_id": null,
        "qty": 0.0092,
        "price_usd": null,
        "usd_value": 0.0,
        "change_24h_pct": null,
        "avg_buy": null,
        "pnl_pct": null,
        "is_stablecoin": false
      }
    ],
    "open_orders": [],
    "recent_trades": [],
    "prices": {
      "BABYUSD": {
        "bid": 0.01289,
        "ask": 0.01291,
        "last": 0.01291,
        "high_24h": 0.01409,
        "low_24h": 0.01274,
        "volume_24h": 3860617.20535,
        "vwap_24h": 0.013208042,
        "trades_24h": 425
      },
      "EIGENUSD": {
        "bid": 0.2034,
        "ask": 0.2036,
        "last": 0.2034,
        "high_24h": 0.2203,
        "low_24h": 0.1981,
        "volume_24h": 300746.75618,
        "vwap_24h": 0.2089174,
        "trades_24h": 769
      },
      "XETHZUSD": {
        "bid": 2192.9,
        "ask": 2193.01,
        "last": 2192.9,
        "high_24h": 2350.41,
        "low_24h": 2153.94,
        "volume_24h": 33526.46081192,
        "vwap_24h": 2246.73882,
        "trades_24h": 30207
      },
      "OPNUSD": {
        "bid": 0.2714,
        "ask": 0.2741,
        "last": 0.2739,
        "high_24h": 0.3064,
        "low_24h": 0.2457,
        "volume_24h": 344677.97113,
        "vwap_24h": 0.27816842,
        "trades_24h": 688
      },
      "PENGUUSD": {
        "bid": 0.007477,
        "ask": 0.007478,
        "last": 0.007457,
        "high_24h": 0.008303,
        "low_24h": 0.007277,
        "volume_24h": 204021338.4613,
        "vwap_24h": 0.007812668,
        "trades_24h": 5955
      },
      "SOLUSD": {
        "bid": 89.98,
        "ask": 89.99,
        "last": 89.99,
        "high_24h": 95.63,
        "low_24h": 88.6,
        "volume_24h": 383723.47324002,
        "vwap_24h": 91.69421,
        "trades_24h": 22431
      },
      "XXBTZUSD": {
        "bid": 71118.1,
        "ask": 71118.2,
        "last": 71118.1,
        "high_24h": 74682.3,
        "low_24h": 70500.0,
        "volume_24h": 2874.806008,
        "vwap_24h": 72279.38846,
        "trades_24h": 67371
      }
    }
  }
}