{
  "generated_at": "2026-03-21T20:47:25Z",
  "exchange": "kraken",
  "cache_hit": false,
  "portfolio": {
    "total_usd": 16.02,
    "stablecoins_usd": 0.01,
    "balances": [
      {
        "asset": "PENGU",
        "symbol": "PENGU",
        "coingecko_id": "pudgy-penguins",
        "qty": 1873.2,
        "price_usd": 0.00712507,
        "usd_value": 13.35,
        "change_24h_pct": 0.89,
        "avg_buy": null,
        "pnl_pct": null,
        "is_stablecoin": false
      },
      {
        "asset": "XXBT",
        "symbol": "BT",
        "coingecko_id": "bitcoin",
        "qty": 2.364e-05,
        "price_usd": 70464,
        "usd_value": 1.67,
        "change_24h_pct": 0.69,
        "avg_buy": 90111.0,
        "pnl_pct": -21.8,
        "is_stablecoin": false
      },
      {
        "asset": "OPN",
        "symbol": "OPN",
        "coingecko_id": "opinion",
        "qty": 3.498,
        "price_usd": 0.282132,
        "usd_value": 0.99,
        "change_24h_pct": 0.29,
        "avg_buy": 0.3326,
        "pnl_pct": -15.2,
        "is_stablecoin": false
      },
      {
        "asset": "USDT",
        "symbol": "USDT",
        "coingecko_id": "tether",
        "qty": 0.01001724,
        "price_usd": 0.999788,
        "usd_value": 0.01,
        "change_24h_pct": -0.01,
        "avg_buy": null,
        "pnl_pct": null,
        "is_stablecoin": true
      },
      {
        "asset": "XETH",
        "symbol": "ETH",
        "coingecko_id": "ethereum",
        "qty": 4.0016e-06,
        "price_usd": 2155.23,
        "usd_value": 0.01,
        "change_24h_pct": 1.14,
        "avg_buy": 3151.0,
        "pnl_pct": -31.6,
        "is_stablecoin": false
      },
      {
        "asset": "BABY",
        "symbol": "BABY",
        "coingecko_id": "babylon",
        "qty": 0.00348,
        "price_usd": 0.01389781,
        "usd_value": 0.0,
        "change_24h_pct": 6.58,
        "avg_buy": 0.028,
        "pnl_pct": -50.4,
        "is_stablecoin": false
      },
      {
        "asset": "EIGEN",
        "symbol": "EIGEN",
        "coingecko_id": "eigenlayer",
        "qty": 0.003366,
        "price_usd": 0.201446,
        "usd_value": 0.0,
        "change_24h_pct": 5.33,
        "avg_buy": 0.3,
        "pnl_pct": -32.9,
        "is_stablecoin": false
      },
      {
        "asset": "ETH.B",
        "symbol": "ETH.B",
        "coingecko_id": null,
        "qty": 0.0018672113,
        "price_usd": null,
        "usd_value": 0.0,
        "change_24h_pct": null,
        "avg_buy": null,
        "pnl_pct": null,
        "is_stablecoin": false
      },
      {
        "asset": "SOL",
        "symbol": "SOL",
        "coingecko_id": "solana",
        "qty": 6.2624e-06,
        "price_usd": 90.16,
        "usd_value": 0.0,
        "change_24h_pct": 1.5,
        "avg_buy": 151.0,
        "pnl_pct": -40.3,
        "is_stablecoin": false
      },
      {
        "asset": "USDG",
        "symbol": "USDG",
        "coingecko_id": null,
        "qty": 1.08310033,
        "price_usd": null,
        "usd_value": 0.0,
        "change_24h_pct": null,
        "avg_buy": null,
        "pnl_pct": null,
        "is_stablecoin": false
      },
      {
        "asset": "XBT.B",
        "symbol": "XBT.B",
        "coingecko_id": null,
        "qty": 6.38547e-05,
        "price_usd": null,
        "usd_value": 0.0,
        "change_24h_pct": null,
        "avg_buy": null,
        "pnl_pct": null,
        "is_stablecoin": false
      },
      {
        "asset": "XBT.M",
        "symbol": "XBT.M",
        "coingecko_id": null,
        "qty": 1.04627e-05,
        "price_usd": null,
        "usd_value": 0.0,
        "change_24h_pct": null,
        "avg_buy": null,
        "pnl_pct": null,
        "is_stablecoin": false
      },
      {
        "asset": "ZEUR",
        "symbol": "ZEUR",
        "coingecko_id": null,
        "qty": 0.0092,
        "price_usd": null,
        "usd_value": 0.0,
        "change_24h_pct": null,
        "avg_buy": null,
        "pnl_pct": null,
        "is_stablecoin": false
      }
    ],
    "open_orders": [],
    "recent_trades": [],
    "prices": {
      "BABYUSD": {
        "bid": 0.01381,
        "ask": 0.01386,
        "last": 0.01394,
        "high_24h": 0.01403,
        "low_24h": 0.0131,
        "volume_24h": 3963965.07513,
        "vwap_24h": 0.013445219,
        "trades_24h": 364
      },
      "EIGENUSD": {
        "bid": 0.2013,
        "ask": 0.2015,
        "last": 0.2013,
        "high_24h": 0.205,
        "low_24h": 0.192,
        "volume_24h": 185750.13085,
        "vwap_24h": 0.2007533,
        "trades_24h": 404
      },
      "XETHZUSD": {
        "bid": 2155.55,
        "ask": 2155.56,
        "last": 2155.56,
        "high_24h": 2168.02,
        "low_24h": 2130.51,
        "volume_24h": 14965.38598503,
        "vwap_24h": 2150.92073,
        "trades_24h": 15455
      },
      "OPNUSD": {
        "bid": 0.2817,
        "ask": 0.2825,
        "last": 0.2813,
        "high_24h": 0.2895,
        "low_24h": 0.2609,
        "volume_24h": 616293.20701,
        "vwap_24h": 0.27668538,
        "trades_24h": 1626
      },
      "PENGUUSD": {
        "bid": 0.00714,
        "ask": 0.007143,
        "last": 0.00714,
        "high_24h": 0.007202,
        "low_24h": 0.007011,
        "volume_24h": 51878782.39615,
        "vwap_24h": 0.007108092,
        "trades_24h": 1349
      },
      "SOLUSD": {
        "bid": 90.12,
        "ask": 90.13,
        "last": 90.13,
        "high_24h": 90.81,
        "low_24h": 88.8,
        "volume_24h": 154256.22855294,
        "vwap_24h": 90.00501,
        "trades_24h": 10785
      },
      "XXBTZUSD": {
        "bid": 70469.2,
        "ask": 70469.3,
        "last": 70469.3,
        "high_24h": 71071.7,
        "low_24h": 69952.2,
        "volume_24h": 875.05311269,
        "vwap_24h": 70598.2022,
        "trades_24h": 28869
      }
    }
  }
}