{
  "generated_at": "2026-03-24T11:38:35Z",
  "exchange": "kraken",
  "cache_hit": false,
  "portfolio": {
    "total_usd": 15.6,
    "stablecoins_usd": 0.01,
    "balances": [
      {
        "asset": "PENGU",
        "symbol": "PENGU",
        "coingecko_id": "pudgy-penguins",
        "qty": 1873.2359,
        "price_usd": 0.00698321,
        "usd_value": 13.08,
        "change_24h_pct": -0.16,
        "avg_buy": null,
        "pnl_pct": null,
        "is_stablecoin": false
      },
      {
        "asset": "XXBT",
        "symbol": "BTC",
        "coingecko_id": "bitcoin",
        "qty": 2.364e-05,
        "price_usd": 71147,
        "usd_value": 1.68,
        "change_24h_pct": 0.98,
        "avg_buy": 90111.0,
        "pnl_pct": -21.0,
        "is_stablecoin": false
      },
      {
        "asset": "OPN",
        "symbol": "OPN",
        "coingecko_id": "opinion",
        "qty": 3.498,
        "price_usd": 0.233069,
        "usd_value": 0.82,
        "change_24h_pct": -7.49,
        "avg_buy": 0.3326,
        "pnl_pct": -29.9,
        "is_stablecoin": false
      },
      {
        "asset": "USDT",
        "symbol": "USDT",
        "coingecko_id": "tether",
        "qty": 0.01002492,
        "price_usd": 0.999635,
        "usd_value": 0.01,
        "change_24h_pct": -0.0,
        "avg_buy": null,
        "pnl_pct": null,
        "is_stablecoin": true
      },
      {
        "asset": "XETH",
        "symbol": "ETH",
        "coingecko_id": "ethereum",
        "qty": 4.0023e-06,
        "price_usd": 2166.4,
        "usd_value": 0.01,
        "change_24h_pct": 0.43,
        "avg_buy": 3151.0,
        "pnl_pct": -31.2,
        "is_stablecoin": false
      },
      {
        "asset": "BABY",
        "symbol": "BABY",
        "coingecko_id": "babylon",
        "qty": 0.0038,
        "price_usd": 0.01380429,
        "usd_value": 0.0,
        "change_24h_pct": -3.56,
        "avg_buy": 0.028,
        "pnl_pct": -50.7,
        "is_stablecoin": false
      },
      {
        "asset": "EIGEN",
        "symbol": "EIGEN",
        "coingecko_id": "eigenlayer",
        "qty": 0.003627,
        "price_usd": 0.196335,
        "usd_value": 0.0,
        "change_24h_pct": -0.21,
        "avg_buy": 0.3,
        "pnl_pct": -34.6,
        "is_stablecoin": false
      },
      {
        "asset": "ETH.B",
        "symbol": "ETH.B",
        "coingecko_id": null,
        "qty": 0.0018678791,
        "price_usd": null,
        "usd_value": 0.0,
        "change_24h_pct": null,
        "avg_buy": null,
        "pnl_pct": null,
        "is_stablecoin": false
      },
      {
        "asset": "SOL",
        "symbol": "SOL",
        "coingecko_id": "solana",
        "qty": 6.265e-06,
        "price_usd": 91.61,
        "usd_value": 0.0,
        "change_24h_pct": 1.53,
        "avg_buy": 151.0,
        "pnl_pct": -39.3,
        "is_stablecoin": false
      },
      {
        "asset": "USDG",
        "symbol": "USDG",
        "coingecko_id": null,
        "qty": 1.08398253,
        "price_usd": null,
        "usd_value": 0.0,
        "change_24h_pct": null,
        "avg_buy": null,
        "pnl_pct": null,
        "is_stablecoin": false
      },
      {
        "asset": "XBT.B",
        "symbol": "XBT.B",
        "coingecko_id": null,
        "qty": 6.38565e-05,
        "price_usd": null,
        "usd_value": 0.0,
        "change_24h_pct": null,
        "avg_buy": null,
        "pnl_pct": null,
        "is_stablecoin": false
      },
      {
        "asset": "XBT.M",
        "symbol": "XBT.M",
        "coingecko_id": null,
        "qty": 1.04629e-05,
        "price_usd": null,
        "usd_value": 0.0,
        "change_24h_pct": null,
        "avg_buy": null,
        "pnl_pct": null,
        "is_stablecoin": false
      },
      {
        "asset": "ZEUR",
        "symbol": "ZEUR",
        "coingecko_id": null,
        "qty": 0.0092,
        "price_usd": null,
        "usd_value": 0.0,
        "change_24h_pct": null,
        "avg_buy": null,
        "pnl_pct": null,
        "is_stablecoin": false
      }
    ],
    "open_orders": [],
    "recent_trades": [],
    "prices": {
      "BABYUSD": {
        "bid": 0.01379,
        "ask": 0.01382,
        "last": 0.01379,
        "high_24h": 0.01476,
        "low_24h": 0.0137,
        "volume_24h": 2331800.25857,
        "vwap_24h": 0.01419642,
        "trades_24h": 384
      },
      "EIGENUSD": {
        "bid": 0.1964,
        "ask": 0.1966,
        "last": 0.1963,
        "high_24h": 0.2006,
        "low_24h": 0.1929,
        "volume_24h": 112049.21456,
        "vwap_24h": 0.1965553,
        "trades_24h": 246
      },
      "XETHZUSD": {
        "bid": 2167.92,
        "ask": 2167.93,
        "last": 2167.72,
        "high_24h": 2191.5,
        "low_24h": 2107.87,
        "volume_24h": 50835.08819628,
        "vwap_24h": 2144.89081,
        "trades_24h": 34687
      },
      "OPNUSD": {
        "bid": 0.2305,
        "ask": 0.2324,
        "last": 0.2329,
        "high_24h": 0.2493,
        "low_24h": 0.2269,
        "volume_24h": 215529.42911,
        "vwap_24h": 0.23753952,
        "trades_24h": 411
      },
      "PENGUUSD": {
        "bid": 0.007001,
        "ask": 0.007002,
        "last": 0.006992,
        "high_24h": 0.007204,
        "low_24h": 0.00688,
        "volume_24h": 80384860.29816,
        "vwap_24h": 0.006999281,
        "trades_24h": 2574
      },
      "SOLUSD": {
        "bid": 91.83,
        "ask": 91.84,
        "last": 91.83,
        "high_24h": 92.21,
        "low_24h": 88.34,
        "volume_24h": 324977.35758658,
        "vwap_24h": 90.96571,
        "trades_24h": 20006
      },
      "XXBTZUSD": {
        "bid": 71157.1,
        "ask": 71157.2,
        "last": 71157.1,
        "high_24h": 71816.6,
        "low_24h": 69669.6,
        "volume_24h": 2288.18092041,
        "vwap_24h": 70776.40222,
        "trades_24h": 61089
      }
    }
  }
}